gradle.properties
hexdoc_hexcellular/__gradle_version__.py
hexdoc_hexcellular/__init__.py
hexdoc_hexcellular/__version__.py
hexdoc_hexcellular/_hooks.py
hexdoc_hexcellular/py.typed
hexdoc_hexcellular/_export/.gitignore
hexdoc_hexcellular/_export/__init__.py
hexdoc_hexcellular/_export/generated/__init__.py
hexdoc_hexcellular/_export/generated/hexcellular.hexdoc.json
hexdoc_hexcellular/_export/generated/hexcellular.patterns.hexdoc.json
hexdoc_hexcellular/_export/generated/assets/hexcasting/lang/en_us.flatten.json5
hexdoc_hexcellular/_export/generated/assets/hexcasting/patchouli_books/thehexbook/en_us/entries/properties.json
hexdoc_hexcellular/_export/generated/assets/hexcellular/lang/en_us.json
hexdoc_hexcellular/_export/generated/assets/hexcellular/lang/zh_cn.json
hexdoc_hexcellular/_templates/__init__.py
hexdoc_hexcellular/_templates/index.css.jinja
hexdoc_hexcellular-1.0.4.1.0.0.dist-info/METADATA
hexdoc_hexcellular-1.0.4.1.0.0.dist-info/WHEEL
hexdoc_hexcellular-1.0.4.1.0.0.dist-info/entry_points.txt
hexdoc_hexcellular-1.0.4.1.0.0.dist-info/licenses/LICENSE
hexdoc_hexcellular-1.0.4.1.0.0.dist-info/RECORD
